solidwrap/__init__.py
solidwrap/containers.py
solidwrap/logger.py
solidwrap/solidwrap.py
solidwrap/utilities.py
solidwrap-2.2.1.dist-info/METADATA
solidwrap-2.2.1.dist-info/WHEEL
solidwrap-2.2.1.dist-info/licenses/LICENSE
solidwrap-2.2.1.dist-info/RECORD
