Metadata-Version: 2.3
Name: solidwrap
Version: 2.2.1
Summary: Wrapper for SolidWorks and PDM APIs for a streamlined, Pythonic workflow.
Project-URL: Homepage, https://github.com/SeanYeatts/SolidWrap/tree/main
Project-URL: Bug Tracker, https://github.com/users/SeanYeatts/projects/6/views/1
Author: Sean Yeatts
License: MIT License
License-File: LICENSE
Classifier: License :: OSI Approved :: MIT License
Classifier: Operating System :: Microsoft :: Windows
Classifier: Programming Language :: Python :: 3
Requires-Python: >=3.7
